winrm_mcp_server/__init__.py
winrm_mcp_server/config.py
winrm_mcp_server/exceptions.py
winrm_mcp_server/server.py
winrm_mcp_server/winrm_client.py
winrm_mcp_server-0.1.3.dist-info/METADATA
winrm_mcp_server-0.1.3.dist-info/WHEEL
winrm_mcp_server-0.1.3.dist-info/entry_points.txt
winrm_mcp_server-0.1.3.dist-info/licenses/LICENSE
winrm_mcp_server-0.1.3.dist-info/RECORD
