Metadata-Version: 2.4
Name: winrm-mcp-server
Version: 0.1.3
Summary: A Model Context Protocol (MCP) server for executing PowerShell commands on remote Windows machines via WinRM
Project-URL: Homepage, https://github.com/antonvano_microsoft/winrm-mcp-server
Project-URL: Repository, https://github.com/antonvano_microsoft/winrm-mcp-server
Project-URL: Documentation, https://github.com/antonvano_microsoft/winrm-mcp-server#readme
Project-URL: Bug Tracker, https://github.com/antonvano_microsoft/winrm-mcp-server/issues
Author-email: Anton Vanco <vanco.anton@gmail.com>
License-Expression: MIT
License-File: LICENSE
Keywords: automation,mcp,powershell,remote,windows,winrm
Classifier: Development Status :: 4 - Beta
Classifier: Intended Audience :: Developers
Classifier: License :: OSI Approved :: MIT License
Classifier: Operating System :: OS Independent
Classifier: Programming Language :: Python :: 3
Classifier: Programming Language :: Python :: 3.10
Classifier: Programming Language :: Python :: 3.11
Classifier: Programming Language :: Python :: 3.12
Classifier: Programming Language :: Python :: 3.13
Classifier: Topic :: Software Development :: Libraries :: Python Modules
Classifier: Topic :: System :: Networking
Classifier: Topic :: System :: Systems Administration
Requires-Python: >=3.10
Requires-Dist: loguru>=0.7.3
Requires-Dist: mcp>=1.12.3
Requires-Dist: pydantic-settings>=2.10.1
Requires-Dist: pydantic>=2.11.7
Requires-Dist: pywinrm>=0.5.0
Provides-Extra: dev
Requires-Dist: black; extra == 'dev'
Requires-Dist: isort; extra == 'dev'
Requires-Dist: mypy; extra == 'dev'
Requires-Dist: pytest; extra == 'dev'
Requires-Dist: pytest-asyncio; extra == 'dev'
